pymarlin/__init__.py
pymarlin/core/__init__.py
pymarlin/core/data_interface.py
pymarlin/core/module_interface.py
pymarlin/core/trainer.py
pymarlin/core/trainer_backend.py
pymarlin/plugins/__init__.py
pymarlin/plugins/base.py
pymarlin/plugins/hfdistill_utils.py
pymarlin/plugins/plugin_module_interface.py
pymarlin/plugins/hf_ner/__init__.py
pymarlin/plugins/hf_ner/data_classes.py
pymarlin/plugins/hf_ner/implementation.py
pymarlin/plugins/hf_ner/module_classes.py
pymarlin/plugins/hf_ner/sequence_labelling_metrics.py
pymarlin/plugins/hf_seq2seq/__init__.py
pymarlin/plugins/hf_seq2seq/data_classes.py
pymarlin/plugins/hf_seq2seq/implementation.py
pymarlin/plugins/hf_seq2seq/metric_utils.py
pymarlin/plugins/hf_seq2seq/module_classes.py
pymarlin/plugins/hf_seq_classification/__init__.py
pymarlin/plugins/hf_seq_classification/data_classes.py
pymarlin/plugins/hf_seq_classification/implementation.py
pymarlin/plugins/hf_seq_classification/metric_utils.py
pymarlin/plugins/hf_seq_classification/module_classes.py
pymarlin/utils/__init__.py
pymarlin/utils/differential_privacy.py
pymarlin/utils/distributed.py
pymarlin/utils/fabrics.py
pymarlin/utils/checkpointer/__init__.py
pymarlin/utils/checkpointer/checkpoint_utils.py
pymarlin/utils/config_parser/__init__.py
pymarlin/utils/config_parser/custom_arg_parser.py
pymarlin/utils/logger/__init__.py
pymarlin/utils/logger/logging_utils.py
pymarlin/utils/misc/__init__.py
pymarlin/utils/misc/misc_utils.py
pymarlin/utils/stats/__init__.py
pymarlin/utils/stats/basic_stats.py
pymarlin/utils/writer/__init__.py
pymarlin/utils/writer/aml.py
pymarlin/utils/writer/base.py
pymarlin/utils/writer/stdout.py
pymarlin/utils/writer/tensorboard.py
pymarlin-0.3.6.dist-info/LICENSE
pymarlin-0.3.6.dist-info/METADATA
pymarlin-0.3.6.dist-info/WHEEL
pymarlin-0.3.6.dist-info/top_level.txt
pymarlin-0.3.6.dist-info/RECORD
