Metadata-Version: 2.1
Name: pymarlin
Version: 0.3.6
Summary: Lightweight Deeplearning Library
Home-page: https://microsoft.github.io/PyMarlin/
Author: ELR Team
Author-email: elrcore@microsoft.com
Classifier: Programming Language :: Python :: 3
Classifier: License :: OSI Approved :: MIT License
Classifier: Operating System :: OS Independent
Requires-Python: >=3.6
License-File: LICENSE
Requires-Dist: torch (<=1.9.1)
Requires-Dist: tqdm
Requires-Dist: tensorboard
Requires-Dist: Pillow
Requires-Dist: azureml-core
Requires-Dist: pyyaml
Requires-Dist: pandas
Provides-Extra: dev
Requires-Dist: pylint ; extra == 'dev'
Requires-Dist: pytest ; extra == 'dev'
Requires-Dist: pytest-cov ; extra == 'dev'
Provides-Extra: plugins
Requires-Dist: transformers ; extra == 'plugins'
Requires-Dist: pandas ; extra == 'plugins'
Requires-Dist: matplotlib ; extra == 'plugins'
Requires-Dist: sklearn ; extra == 'plugins'
Requires-Dist: scipy ; extra == 'plugins'
Requires-Dist: rouge-score ; extra == 'plugins'
